wc18/__init__.py
wc18/countries.json
wc18/teamsgroups.py
wc18/wc18.py
wc18_cli-0.0.1.8.dist-info/METADATA
wc18_cli-0.0.1.8.dist-info/RECORD
wc18_cli-0.0.1.8.dist-info/WHEEL
wc18_cli-0.0.1.8.dist-info/entry_points.txt
wc18_cli-0.0.1.8.dist-info/top_level.txt
