Metadata-Version: 2.1
Name: wc18-cli
Version: 0.0.1.8
Summary: An easy command line interface for the 2018 World Cup
Home-page: https://github.com/SkullCarverCoder/wc18-cli
Author: Juan Hernandez
Author-email: juanl182@gmail.com
License: MIT
Keywords: soccer football worldcup tool cli
Platform: UNKNOWN
Classifier: Development Status :: 4 - Beta
Classifier: Intended Audience :: Developers
Classifier: Topic :: Software Development :: Build Tools
Classifier: License :: OSI Approved :: MIT License
Classifier: Programming Language :: Python :: 3.6
Requires-Dist: click (==6.7)
Requires-Dist: pytz (==2018.4)
Requires-Dist: tzlocal (==1.5.1)
Requires-Dist: requests (==2.18.4)
Requires-Dist: python-dateutil (==2.7.3)
Requires-Dist: colorama (==0.3.9)
